{
  "version": "7",
  "dialect": "sqlite",
  "entries": [
    {
      "idx": 0,
      "version": "6",
      "when": 1725967557147,
      "tag": "0000_broad_raza",
      "breakpoints": true
    },
    {
      "idx": 1,
      "version": "6",
      "when": 1725971693659,
      "tag": "0001_rare_ricochet",
      "breakpoints": true
    },
    {
      "idx": 2,
      "version": "6",
      "when": 1727646521687,
      "tag": "0002_round_tomorrow_man",
      "breakpoints": true
    },
    {
      "idx": 3,
      "version": "6",
      "when": 1727780929505,
      "tag": "0003_misty_crusher_hogan",
      "breakpoints": true
    }
  ]
}